OptimizadorModelos/Funciones_objetivo.py
OptimizadorModelos/Sistema.py
OptimizadorModelos/__init__.py
OptimizadorModelos/calculos.py
OptimizadorModelos/optimizadores.py
OptimizadorModelos-2.2.dist-info/LICENCE.txt
OptimizadorModelos-2.2.dist-info/METADATA
OptimizadorModelos-2.2.dist-info/WHEEL
OptimizadorModelos-2.2.dist-info/top_level.txt
OptimizadorModelos-2.2.dist-info/RECORD
