Metadata-Version: 2.1
Name: OptimizadorModelos
Version: 2.2
Summary: Esperemos que alfin funciones
Author: Luis Corado
Author-email: wichocorado01@gmail.com
Classifier: Programming Language :: Python :: 3
Classifier: License :: OSI Approved :: MIT License
Classifier: Operating System :: OS Independent
License-File: LICENCE.txt
